video2images/__init__.py
video2images/video2images.py
video2images-1.3.data/scripts/video2images
video2images-1.3.dist-info/LICENSE
video2images-1.3.dist-info/METADATA
video2images-1.3.dist-info/WHEEL
video2images-1.3.dist-info/top_level.txt
video2images-1.3.dist-info/RECORD
