Metadata-Version: 2.1
Name: video2images
Version: 1.3
Summary: Video 2 Image converter
Home-page: https://github.com/AbhishekSalian/Video2Images
Author: Abhishek C. Salian
Author-email: abhishek.c.salian@gmail.com
License: MIT License
Platform: windows
Platform: linux
Platform: unix
Requires-Python: >=3.5
Requires-Dist: tqdm
Requires-Dist: imageio
Requires-Dist: moviepy
Requires-Dist: imageio-ffmpeg (>=0.4.2)
